misctools/__init__.py
misctools/misctools.py
zcgtools/__init__.py
zcgtools/zcgtools.py
zcgtools-0.1.dist-info/LICENSE
zcgtools-0.1.dist-info/METADATA
zcgtools-0.1.dist-info/WHEEL
zcgtools-0.1.dist-info/top_level.txt
zcgtools-0.1.dist-info/RECORD
